caller/Fruit.py
caller/__init__.py
caller/entry.py
caller/data/demo.yaml
packagingxx-0.0.1.dist-info/METADATA
packagingxx-0.0.1.dist-info/WHEEL
packagingxx-0.0.1.dist-info/top_level.txt
packagingxx-0.0.1.dist-info/RECORD
