Metadata-Version: 2.1
Name: packagingxx
Version: 0.0.1
Summary: It's a MVP of Python packaging
Home-page: UNKNOWN
Author: Anonymous
License: UNKNOWN
Keywords: demo testing laboratory
Platform: UNKNOWN
Requires-Dist: pyyaml (==5.3.1)
Provides-Extra: develop
Requires-Dist: virtualenv (>=20.1.0) ; extra == 'develop'
Requires-Dist: urllib3 (~=1.26.0) ; extra == 'develop'
Provides-Extra: format
Requires-Dist: pre-commit (==2.8.0) ; extra == 'format'
